{"name":"PAT","slug":"PAT","count":1,"postlist":[{"title":"PAT 1141 Python C++ 解题","slug":"pat/advanced_level/1141","date":"2018-03-20T15:02:54.036Z","updated":"2018-04-19T08:01:32.586Z","comments":true,"path":"api/articles/pat/advanced_level/1141.json","excerpt":"<p>题源：<a href=\"https://www.patest.cn/contests/pat-a-practise/1141\" target=\"_blank\" rel=\"noopener\">https://www.patest.cn/contests/pat-a-practise/1141</a></p><p>注意，对于最后两个测试点，使用 Python 语言会超时，从前三个测试点来看，同样的逻辑下 Python 的速度大概是 C++ 的 14%，嗯，太慢了……<br>","keywords":null,"cover":null,"content":null,"text":"题源：https://www.patest.cn/contests/pat-a-practise/1141注意，对于最后两个测试点，使用 Python 语言会超时，从前三个测试点来看，同样的逻辑下 Python 的速度大概是 C++ 的 14%，嗯，太慢了……<br>OK，照例，","link":"","raw":null,"photos":[],"categories":[],"tags":[{"name":"PAT","slug":"PAT","count":1,"path":"api/tags/PAT.json"}]}]}